track_viz/__init__.py
track_viz/__main__.py
track_viz/heatmap.py
track_viz/input_file.py
track_viz/py.typed
track_viz/speed.py
track_viz/static/Fitbit_logo_RGB.svg
track_viz/static/all.js
track_viz/static/track_viz_favicon.png
track_viz/static/upload.css
track_viz/templates/show_fitbit_runs.html
track_viz/templates/show_graph.html
track_viz/templates/show_heatmap.html
track_viz/templates/upload_heatmap.html
track_viz/templates/upload_speed.html
track_viz/webserver.py
track_viz-0.5.0.dist-info/entry_points.txt
track_viz-0.5.0.dist-info/LICENSE.rst
track_viz-0.5.0.dist-info/WHEEL
track_viz-0.5.0.dist-info/METADATA
track_viz-0.5.0.dist-info/RECORD
