Metadata-Version: 2.1
Name: track-viz
Version: 0.5.0
Summary: Visualize Tracking Data
Home-page: https://github.com/JulienMBABD/track-viz
License: MIT
Author: Julien Rossi
Author-email: mr.julien.rossi@gmail.com
Requires-Python: >=3.8,<4.0
Classifier: Development Status :: 3 - Alpha
Classifier: License :: OSI Approved :: MIT License
Classifier: Programming Language :: Python :: 3
Classifier: Programming Language :: Python :: 3.8
Classifier: Programming Language :: Python :: 3.9
Classifier: Programming Language :: Python :: 3.10
Classifier: Programming Language :: Python :: 3.11
Requires-Dist: Flask (>=2.0.2,<3.0.0)
Requires-Dist: PyYAML (>=6.0,<7.0)
Requires-Dist: altair (>=4.2.0,<5.0.0)
Requires-Dist: click (>=8.0.1,<9.0.0)
Requires-Dist: dash-bootstrap-components (>=1.0.3,<2.0.0)
Requires-Dist: defusedxml (>=0.7.1,<0.8.0)
Requires-Dist: geopandas (>=0.10.2,<0.11.0)
Requires-Dist: geopy (>=2.2.0,<3.0.0)
Requires-Dist: loess (>=2.1.2,<3.0.0)
Requires-Dist: lxml (>=4.6.4,<5.0.0)
Requires-Dist: matplotlib (>=3.5.0,<4.0.0)
Requires-Dist: pandas (>=1.3.4,<2.0.0)
Requires-Dist: plotly (>=5.6.0,<6.0.0)
Requires-Dist: poetry (>=1.1.12,<2.0.0)
Requires-Dist: py-fitbit (>=1.0.1,<2.0.0)
Requires-Dist: python-dotenv (>=0.19.2,<0.20.0)
Requires-Dist: seaborn (>=0.11.2,<0.12.0)
Project-URL: Changelog, https://github.com/JulienMBABD/track-viz/releases
Project-URL: Documentation, https://track-viz.readthedocs.io
Project-URL: Repository, https://github.com/JulienMBABD/track-viz
